balance_domain/__init__.py
balance_domain/entities/__init__.py
balance_domain/entities/bank.py
balance_domain/entities/user.py
balance_domain-0.1.36.dist-info/METADATA
balance_domain-0.1.36.dist-info/WHEEL
balance_domain-0.1.36.dist-info/top_level.txt
balance_domain-0.1.36.dist-info/RECORD
