Metadata-Version: 2.1
Name: balance-domain
Version: 0.1.36
Summary: Objetivos:
Home-page: https://pypi.org/project/balance-domain
Author: Calenzo
Author-email: calenzodevs@gmail.com
License: MIT License
Classifier: Programming Language :: Python :: 3.7
Classifier: Programming Language :: Python :: 3.8
Classifier: Natural Language :: English
Classifier: License :: OSI Approved :: MIT License
Classifier: Operating System :: OS Independent
